afisys_monitor/__init__.py
afisys_monitor/__main__.py
afisys_monitor/interfaces.py
afisys_monitor/ip.py
afisys_monitor/leases.py
afisys_monitor/lxc.py
afisys_monitor/lxd.py
afisys_monitor/module.py
afisys_monitor/monitor.py
afisys_monitor/resolve.py
afisys_monitor/routes.py
afisys_monitor/sensors.py
afisys_monitor-0.2.2.dist-info/entry_points.txt
afisys_monitor-0.2.2.dist-info/LICENSE
afisys_monitor-0.2.2.dist-info/WHEEL
afisys_monitor-0.2.2.dist-info/METADATA
afisys_monitor-0.2.2.dist-info/RECORD
